lambdata_chancedurr/__init__.py
lambdata_chancedurr/mod.py
lambdata_chancedurr-0.0.13.dist-info/LICENSE
lambdata_chancedurr-0.0.13.dist-info/METADATA
lambdata_chancedurr-0.0.13.dist-info/WHEEL
lambdata_chancedurr-0.0.13.dist-info/top_level.txt
lambdata_chancedurr-0.0.13.dist-info/RECORD
