Metadata-Version: 2.1
Name: lambdata-chancedurr
Version: 0.0.13
Summary: A package for learning packages
Home-page: https://github.com/chancedurr
Author: Chance Dare
Author-email: chancedurr@gmail.com
License: UNKNOWN
Platform: UNKNOWN
Classifier: Programming Language :: Python :: 3
Classifier: License :: OSI Approved :: MIT License
Classifier: Operating System :: OS Independent
